{"cameraMode":{"drawMode":0,"name":"Shaded","section":"Shading Mode"},"sceneLighting":true,"audioPlay":false,"sceneViewState":{"showFog":true,"showMaterialUpdate":false,"showSkybox":true,"showFlares":true,"showImageEffects":true,"showParticleSystems":true},"in2DMode":false,"pivot":{"x":9.28010368347168,"y":-5.522578716278076,"z":-2.5599300861358644},"rotation":{"x":0.008226313628256321,"y":0.8360945582389832,"z":0.012542344629764557,"w":-0.5483803749084473},"size":8.617438316345215,"orthographic":false}